{
    "AircraftType": "LAB",
    "DegradationState": "UNDEF_0",
    "FirstNode": 0,
    "LinkArray": [
      {
        "AircraftDataValid": false,
        "DataCapable": false,
        "MADL_UID": 0,
        "NodeID": 0,
        "OperationalState": "NONE",
        "ReceiveRate": "NOT CONNECTED",
        "SearchMode": "NO STATEMENT",
        "Status": "NO STATEMENT",
        "TransmitRate": "NOT CONNECTED",
        "VoiceCapable": false
      },
      {
        "AircraftDataValid": false,
        "DataCapable": false,
        "MADL_UID": 0,
        "NodeID": 0,
        "OperationalState": "NONE",
        "ReceiveRate": "NOT CONNECTED",
        "SearchMode": "NO STATEMENT",
        "Status": "NO STATEMENT",
        "TransmitRate": "NOT CONNECTED",
        "VoiceCapable": false
      }
    ],
    "MADLUID": 0,
    "MIDE": 0,
    "NumNodes": 0,
    "flightID": "F",
    "missionID": 0,
    "nodeID": 0
  }